CNIO_Tagger.py
CNIO_Tagger-0.1.dist-info/DESCRIPTION.rst
CNIO_Tagger-0.1.dist-info/METADATA
CNIO_Tagger-0.1.dist-info/RECORD
CNIO_Tagger-0.1.dist-info/WHEEL
CNIO_Tagger-0.1.dist-info/metadata.json
CNIO_Tagger-0.1.dist-info/top_level.txt
