Metadata-Version: 2.0
Name: CNIO-Tagger
Version: 0.1
Summary: Python Wrapper for the CNIO POS Tagger
Home-page: https://github.com/PlanTL/SPACCC_POS-TAGGER/CNIO_Tagger
Author: Felipe Soares - felipe.soares@bsc.es
Author-email: UNKNOWN
License: UNKNOWN
Platform: UNKNOWN
